libkdv/Atlanta.csv
libkdv/LICENSE.txt
libkdv/__init__.py
libkdv/compute_kdv.py
libkdv/demo.py
libkdv/kdv.py
libkdv/libkdv.dll
libkdv/libkdv_linux.dll
libkdv/libkdv_m2.dll
libkdv/libkdv_mac.dll
libkdv/plot.py
libkdv/utils.py
libkdv-1.1.20.dist-info/METADATA
libkdv-1.1.20.dist-info/WHEEL
libkdv-1.1.20.dist-info/top_level.txt
libkdv-1.1.20.dist-info/RECORD
