Metadata-Version: 2.1
Name: libkdv
Version: 1.1.20
Summary: A library of feature heatmap algorithm
Home-page: https://github.com/libkdv
Author: Tsz Nam Chan,PakLon Ip, Ryan Leong Hou U
Author-email: www.1nick@gmail.com
License: MIT Licence
Keywords: pip,KDE,heatmap,KDV,KeplerGL
Platform: any
